<?xml version="1.0" standalone="no"?>
<?xml-stylesheet type="text/xsl" href="file:///C:/Analog Devices/CrossCore Embedded Studio 2.9.2/System/linker_log.xsl"?>
<DOCUMENT gen_time='Mon Jun 29 02:32:31 2020
'>
<MSG id='03369850' mid='li1050' type='Error' >
<TEXT><![CDATA['_wet' ('wet'): Multiply defined symbol in processor 'p0'.
        Initial definition:     'src\audio_processing.doj'
        Attempted redefinition: 'src\blockProcess.doj']]></TEXT>
</MSG>
<MSG id='03369AC8' mid='li1050' type='Error' >
<TEXT><![CDATA['_time' ('time'): Multiply defined symbol in processor 'p0'.
        Initial definition:     'src\audio_processing.doj'
        Attempted redefinition: 'src\blockProcess.doj']]></TEXT>
</MSG>
<MSG id='03369C88' mid='li1050' type='Error' >
<TEXT><![CDATA['_cf0_g' ('cf0_g'): Multiply defined symbol in processor 'p0'.
        Initial definition:     'src\audio_processing.doj'
        Attempted redefinition: 'src\blockProcess.doj']]></TEXT>
</MSG>
<MSG id='0336D958' mid='li1050' type='Error' >
<TEXT><![CDATA['_cf1_g' ('cf1_g'): Multiply defined symbol in processor 'p0'.
        Initial definition:     'src\audio_processing.doj'
        Attempted redefinition: 'src\blockProcess.doj']]></TEXT>
</MSG>
<MSG id='0336DB18' mid='li1050' type='Error' >
<TEXT><![CDATA['_cf2_g' ('cf2_g'): Multiply defined symbol in processor 'p0'.
        Initial definition:     'src\audio_processing.doj'
        Attempted redefinition: 'src\blockProcess.doj']]></TEXT>
</MSG>
<MSG id='0336DCD8' mid='li1050' type='Error' >
<TEXT><![CDATA['_cf3_g' ('cf3_g'): Multiply defined symbol in processor 'p0'.
        Initial definition:     'src\audio_processing.doj'
        Attempted redefinition: 'src\blockProcess.doj']]></TEXT>
</MSG>
<MSG id='0336DE98' mid='li1050' type='Error' >
<TEXT><![CDATA['_ap0_g' ('ap0_g'): Multiply defined symbol in processor 'p0'.
        Initial definition:     'src\audio_processing.doj'
        Attempted redefinition: 'src\blockProcess.doj']]></TEXT>
</MSG>
<MSG id='0336E058' mid='li1050' type='Error' >
<TEXT><![CDATA['_ap1_g' ('ap1_g'): Multiply defined symbol in processor 'p0'.
        Initial definition:     'src\audio_processing.doj'
        Attempted redefinition: 'src\blockProcess.doj']]></TEXT>
</MSG>
<MSG id='0336F808' mid='li1050' type='Error' >
<TEXT><![CDATA['_ap2_g' ('ap2_g'): Multiply defined symbol in processor 'p0'.
        Initial definition:     'src\audio_processing.doj'
        Attempted redefinition: 'src\blockProcess.doj']]></TEXT>
</MSG>
<MSG id='0336F9C8' mid='li1050' type='Error' >
<TEXT><![CDATA['_cf0_p' ('cf0_p'): Multiply defined symbol in processor 'p0'.
        Initial definition:     'src\audio_processing.doj'
        Attempted redefinition: 'src\blockProcess.doj']]></TEXT>
</MSG>
<MSG id='0336FB88' mid='li1050' type='Error' >
<TEXT><![CDATA['_cf1_p' ('cf1_p'): Multiply defined symbol in processor 'p0'.
        Initial definition:     'src\audio_processing.doj'
        Attempted redefinition: 'src\blockProcess.doj']]></TEXT>
</MSG>
<MSG id='0336FD48' mid='li1050' type='Error' >
<TEXT><![CDATA['_cf2_p' ('cf2_p'): Multiply defined symbol in processor 'p0'.
        Initial definition:     'src\audio_processing.doj'
        Attempted redefinition: 'src\blockProcess.doj']]></TEXT>
</MSG>
<MSG id='0336FF08' mid='li1050' type='Error' >
<TEXT><![CDATA['_cf3_p' ('cf3_p'): Multiply defined symbol in processor 'p0'.
        Initial definition:     'src\audio_processing.doj'
        Attempted redefinition: 'src\blockProcess.doj']]></TEXT>
</MSG>
<MSG id='033700C8' mid='li1050' type='Error' >
<TEXT><![CDATA['_ap0_p' ('ap0_p'): Multiply defined symbol in processor 'p0'.
        Initial definition:     'src\audio_processing.doj'
        Attempted redefinition: 'src\blockProcess.doj']]></TEXT>
</MSG>
<MSG id='03370288' mid='li1050' type='Error' >
<TEXT><![CDATA['_ap1_p' ('ap1_p'): Multiply defined symbol in processor 'p0'.
        Initial definition:     'src\audio_processing.doj'
        Attempted redefinition: 'src\blockProcess.doj']]></TEXT>
</MSG>
<MSG id='03370448' mid='li1050' type='Error' >
<TEXT><![CDATA['_ap2_p' ('ap2_p'): Multiply defined symbol in processor 'p0'.
        Initial definition:     'src\audio_processing.doj'
        Attempted redefinition: 'src\blockProcess.doj']]></TEXT>
</MSG>
<MSG id='03370608' mid='li1050' type='Error' >
<TEXT><![CDATA['_cfbuf0' ('cfbuf0'): Multiply defined symbol in processor 'p0'.
        Initial definition:     'src\audio_processing.doj'
        Attempted redefinition: 'src\blockProcess.doj']]></TEXT>
</MSG>
<MSG id='033707C8' mid='li1050' type='Error' >
<TEXT><![CDATA['_cfbuf1' ('cfbuf1'): Multiply defined symbol in processor 'p0'.
        Initial definition:     'src\audio_processing.doj'
        Attempted redefinition: 'src\blockProcess.doj']]></TEXT>
</MSG>
<MSG id='03370988' mid='li1050' type='Error' >
<TEXT><![CDATA['_cfbuf2' ('cfbuf2'): Multiply defined symbol in processor 'p0'.
        Initial definition:     'src\audio_processing.doj'
        Attempted redefinition: 'src\blockProcess.doj']]></TEXT>
</MSG>
<MSG id='03370B48' mid='li1050' type='Error' >
<TEXT><![CDATA['_cfbuf3' ('cfbuf3'): Multiply defined symbol in processor 'p0'.
        Initial definition:     'src\audio_processing.doj'
        Attempted redefinition: 'src\blockProcess.doj']]></TEXT>
</MSG>
<MSG id='03370D08' mid='li1050' type='Error' >
<TEXT><![CDATA['_apbuf0' ('apbuf0'): Multiply defined symbol in processor 'p0'.
        Initial definition:     'src\audio_processing.doj'
        Attempted redefinition: 'src\blockProcess.doj']]></TEXT>
</MSG>
<MSG id='03370EC8' mid='li1050' type='Error' >
<TEXT><![CDATA['_apbuf1' ('apbuf1'): Multiply defined symbol in processor 'p0'.
        Initial definition:     'src\audio_processing.doj'
        Attempted redefinition: 'src\blockProcess.doj']]></TEXT>
</MSG>
<MSG id='03371088' mid='li1050' type='Error' >
<TEXT><![CDATA['_apbuf2' ('apbuf2'): Multiply defined symbol in processor 'p0'.
        Initial definition:     'src\audio_processing.doj'
        Attempted redefinition: 'src\blockProcess.doj']]></TEXT>
</MSG>
<MSG id='03371248' mid='li1050' type='Error' >
<TEXT><![CDATA['_wet' ('wet'): Multiply defined symbol in processor 'p0'.
        Initial definition:     'src\audio_processing.doj'
        Attempted redefinition: 'src\main.doj']]></TEXT>
</MSG>
<MSG id='03371408' mid='li1050' type='Error' >
<TEXT><![CDATA['_time' ('time'): Multiply defined symbol in processor 'p0'.
        Initial definition:     'src\audio_processing.doj'
        Attempted redefinition: 'src\main.doj']]></TEXT>
</MSG>
<MSG id='033715C8' mid='li1050' type='Error' >
<TEXT><![CDATA['_cf0_g' ('cf0_g'): Multiply defined symbol in processor 'p0'.
        Initial definition:     'src\audio_processing.doj'
        Attempted redefinition: 'src\main.doj']]></TEXT>
</MSG>
<MSG id='03372C38' mid='li1050' type='Error' >
<TEXT><![CDATA['_cf1_g' ('cf1_g'): Multiply defined symbol in processor 'p0'.
        Initial definition:     'src\audio_processing.doj'
        Attempted redefinition: 'src\main.doj']]></TEXT>
</MSG>
<MSG id='03372DF8' mid='li1050' type='Error' >
<TEXT><![CDATA['_cf2_g' ('cf2_g'): Multiply defined symbol in processor 'p0'.
        Initial definition:     'src\audio_processing.doj'
        Attempted redefinition: 'src\main.doj']]></TEXT>
</MSG>
<MSG id='03372FB8' mid='li1050' type='Error' >
<TEXT><![CDATA['_cf3_g' ('cf3_g'): Multiply defined symbol in processor 'p0'.
        Initial definition:     'src\audio_processing.doj'
        Attempted redefinition: 'src\main.doj']]></TEXT>
</MSG>
<MSG id='03373178' mid='li1050' type='Error' >
<TEXT><![CDATA['_ap0_g' ('ap0_g'): Multiply defined symbol in processor 'p0'.
        Initial definition:     'src\audio_processing.doj'
        Attempted redefinition: 'src\main.doj']]></TEXT>
</MSG>
<MSG id='03373338' mid='li1050' type='Error' >
<TEXT><![CDATA['_ap1_g' ('ap1_g'): Multiply defined symbol in processor 'p0'.
        Initial definition:     'src\audio_processing.doj'
        Attempted redefinition: 'src\main.doj']]></TEXT>
</MSG>
<MSG id='033734F8' mid='li1050' type='Error' >
<TEXT><![CDATA['_ap2_g' ('ap2_g'): Multiply defined symbol in processor 'p0'.
        Initial definition:     'src\audio_processing.doj'
        Attempted redefinition: 'src\main.doj']]></TEXT>
</MSG>
<MSG id='033736B8' mid='li1050' type='Error' >
<TEXT><![CDATA['_cf0_p' ('cf0_p'): Multiply defined symbol in processor 'p0'.
        Initial definition:     'src\audio_processing.doj'
        Attempted redefinition: 'src\main.doj']]></TEXT>
</MSG>
<MSG id='03373878' mid='li1050' type='Error' >
<TEXT><![CDATA['_cf1_p' ('cf1_p'): Multiply defined symbol in processor 'p0'.
        Initial definition:     'src\audio_processing.doj'
        Attempted redefinition: 'src\main.doj']]></TEXT>
</MSG>
<MSG id='03373A38' mid='li1050' type='Error' >
<TEXT><![CDATA['_cf2_p' ('cf2_p'): Multiply defined symbol in processor 'p0'.
        Initial definition:     'src\audio_processing.doj'
        Attempted redefinition: 'src\main.doj']]></TEXT>
</MSG>
<MSG id='03373BF8' mid='li1050' type='Error' >
<TEXT><![CDATA['_cf3_p' ('cf3_p'): Multiply defined symbol in processor 'p0'.
        Initial definition:     'src\audio_processing.doj'
        Attempted redefinition: 'src\main.doj']]></TEXT>
</MSG>
<MSG id='03373DB8' mid='li1050' type='Error' >
<TEXT><![CDATA['_ap0_p' ('ap0_p'): Multiply defined symbol in processor 'p0'.
        Initial definition:     'src\audio_processing.doj'
        Attempted redefinition: 'src\main.doj']]></TEXT>
</MSG>
<MSG id='03373F78' mid='li1050' type='Error' >
<TEXT><![CDATA['_ap1_p' ('ap1_p'): Multiply defined symbol in processor 'p0'.
        Initial definition:     'src\audio_processing.doj'
        Attempted redefinition: 'src\main.doj']]></TEXT>
</MSG>
<MSG id='03374138' mid='li1050' type='Error' >
<TEXT><![CDATA['_ap2_p' ('ap2_p'): Multiply defined symbol in processor 'p0'.
        Initial definition:     'src\audio_processing.doj'
        Attempted redefinition: 'src\main.doj']]></TEXT>
</MSG>
<MSG id='033742F8' mid='li1050' type='Error' >
<TEXT><![CDATA['_cfbuf0' ('cfbuf0'): Multiply defined symbol in processor 'p0'.
        Initial definition:     'src\audio_processing.doj'
        Attempted redefinition: 'src\main.doj']]></TEXT>
</MSG>
<MSG id='033744B8' mid='li1050' type='Error' >
<TEXT><![CDATA['_cfbuf1' ('cfbuf1'): Multiply defined symbol in processor 'p0'.
        Initial definition:     'src\audio_processing.doj'
        Attempted redefinition: 'src\main.doj']]></TEXT>
</MSG>
<MSG id='03374678' mid='li1050' type='Error' >
<TEXT><![CDATA['_cfbuf2' ('cfbuf2'): Multiply defined symbol in processor 'p0'.
        Initial definition:     'src\audio_processing.doj'
        Attempted redefinition: 'src\main.doj']]></TEXT>
</MSG>
<MSG id='03374838' mid='li1050' type='Error' >
<TEXT><![CDATA['_cfbuf3' ('cfbuf3'): Multiply defined symbol in processor 'p0'.
        Initial definition:     'src\audio_processing.doj'
        Attempted redefinition: 'src\main.doj']]></TEXT>
</MSG>
<MSG id='033749F8' mid='li1050' type='Error' >
<TEXT><![CDATA['_apbuf0' ('apbuf0'): Multiply defined symbol in processor 'p0'.
        Initial definition:     'src\audio_processing.doj'
        Attempted redefinition: 'src\main.doj']]></TEXT>
</MSG>
<MSG id='03375038' mid='li1050' type='Error' >
<TEXT><![CDATA['_apbuf1' ('apbuf1'): Multiply defined symbol in processor 'p0'.
        Initial definition:     'src\audio_processing.doj'
        Attempted redefinition: 'src\main.doj']]></TEXT>
</MSG>
<MSG id='033751F8' mid='li1050' type='Error' >
<TEXT><![CDATA['_apbuf2' ('apbuf2'): Multiply defined symbol in processor 'p0'.
        Initial definition:     'src\audio_processing.doj'
        Attempted redefinition: 'src\main.doj']]></TEXT>
</MSG>
<MSG id='033753B8' mid='li1050' type='Error' >
<TEXT><![CDATA['_wet' ('wet'): Multiply defined symbol in processor 'p0'.
        Initial definition:     'src\audio_processing.doj'
        Attempted redefinition: 'src\reverb.doj']]></TEXT>
</MSG>
<MSG id='03375578' mid='li1050' type='Error' >
<TEXT><![CDATA['_time' ('time'): Multiply defined symbol in processor 'p0'.
        Initial definition:     'src\audio_processing.doj'
        Attempted redefinition: 'src\reverb.doj']]></TEXT>
</MSG>
<MSG id='03375738' mid='li1050' type='Error' >
<TEXT><![CDATA['_cf0_g' ('cf0_g'): Multiply defined symbol in processor 'p0'.
        Initial definition:     'src\audio_processing.doj'
        Attempted redefinition: 'src\reverb.doj']]></TEXT>
</MSG>
<MSG id='033758F8' mid='li1050' type='Error' >
<TEXT><![CDATA['_cf1_g' ('cf1_g'): Multiply defined symbol in processor 'p0'.
        Initial definition:     'src\audio_processing.doj'
        Attempted redefinition: 'src\reverb.doj']]></TEXT>
</MSG>
<MSG id='03375AB8' mid='li1050' type='Error' >
<TEXT><![CDATA['_cf2_g' ('cf2_g'): Multiply defined symbol in processor 'p0'.
        Initial definition:     'src\audio_processing.doj'
        Attempted redefinition: 'src\reverb.doj']]></TEXT>
</MSG>
<MSG id='03375C78' mid='li1050' type='Error' >
<TEXT><![CDATA['_cf3_g' ('cf3_g'): Multiply defined symbol in processor 'p0'.
        Initial definition:     'src\audio_processing.doj'
        Attempted redefinition: 'src\reverb.doj']]></TEXT>
</MSG>
<MSG id='03375E38' mid='li1050' type='Error' >
<TEXT><![CDATA['_ap0_g' ('ap0_g'): Multiply defined symbol in processor 'p0'.
        Initial definition:     'src\audio_processing.doj'
        Attempted redefinition: 'src\reverb.doj']]></TEXT>
</MSG>
<MSG id='03375FF8' mid='li1050' type='Error' >
<TEXT><![CDATA['_ap1_g' ('ap1_g'): Multiply defined symbol in processor 'p0'.
        Initial definition:     'src\audio_processing.doj'
        Attempted redefinition: 'src\reverb.doj']]></TEXT>
</MSG>
<MSG id='033761B8' mid='li1050' type='Error' >
<TEXT><![CDATA['_ap2_g' ('ap2_g'): Multiply defined symbol in processor 'p0'.
        Initial definition:     'src\audio_processing.doj'
        Attempted redefinition: 'src\reverb.doj']]></TEXT>
</MSG>
<MSG id='03376378' mid='li1050' type='Error' >
<TEXT><![CDATA['_cf0_p' ('cf0_p'): Multiply defined symbol in processor 'p0'.
        Initial definition:     'src\audio_processing.doj'
        Attempted redefinition: 'src\reverb.doj']]></TEXT>
</MSG>
<MSG id='03376538' mid='li1050' type='Error' >
<TEXT><![CDATA['_cf1_p' ('cf1_p'): Multiply defined symbol in processor 'p0'.
        Initial definition:     'src\audio_processing.doj'
        Attempted redefinition: 'src\reverb.doj']]></TEXT>
</MSG>
<MSG id='033766F8' mid='li1050' type='Error' >
<TEXT><![CDATA['_cf2_p' ('cf2_p'): Multiply defined symbol in processor 'p0'.
        Initial definition:     'src\audio_processing.doj'
        Attempted redefinition: 'src\reverb.doj']]></TEXT>
</MSG>
<MSG id='033768B8' mid='li1050' type='Error' >
<TEXT><![CDATA['_cf3_p' ('cf3_p'): Multiply defined symbol in processor 'p0'.
        Initial definition:     'src\audio_processing.doj'
        Attempted redefinition: 'src\reverb.doj']]></TEXT>
</MSG>
<MSG id='03376A78' mid='li1050' type='Error' >
<TEXT><![CDATA['_ap0_p' ('ap0_p'): Multiply defined symbol in processor 'p0'.
        Initial definition:     'src\audio_processing.doj'
        Attempted redefinition: 'src\reverb.doj']]></TEXT>
</MSG>
<MSG id='03376C38' mid='li1050' type='Error' >
<TEXT><![CDATA['_ap1_p' ('ap1_p'): Multiply defined symbol in processor 'p0'.
        Initial definition:     'src\audio_processing.doj'
        Attempted redefinition: 'src\reverb.doj']]></TEXT>
</MSG>
<MSG id='03376DF8' mid='li1050' type='Error' >
<TEXT><![CDATA['_ap2_p' ('ap2_p'): Multiply defined symbol in processor 'p0'.
        Initial definition:     'src\audio_processing.doj'
        Attempted redefinition: 'src\reverb.doj']]></TEXT>
</MSG>
<MSG id='03377038' mid='li1050' type='Error' >
<TEXT><![CDATA['_cfbuf0' ('cfbuf0'): Multiply defined symbol in processor 'p0'.
        Initial definition:     'src\audio_processing.doj'
        Attempted redefinition: 'src\reverb.doj']]></TEXT>
</MSG>
<MSG id='033771F8' mid='li1050' type='Error' >
<TEXT><![CDATA['_cfbuf1' ('cfbuf1'): Multiply defined symbol in processor 'p0'.
        Initial definition:     'src\audio_processing.doj'
        Attempted redefinition: 'src\reverb.doj']]></TEXT>
</MSG>
<MSG id='033773B8' mid='li1050' type='Error' >
<TEXT><![CDATA['_cfbuf2' ('cfbuf2'): Multiply defined symbol in processor 'p0'.
        Initial definition:     'src\audio_processing.doj'
        Attempted redefinition: 'src\reverb.doj']]></TEXT>
</MSG>
<MSG id='03377578' mid='li1050' type='Error' >
<TEXT><![CDATA['_cfbuf3' ('cfbuf3'): Multiply defined symbol in processor 'p0'.
        Initial definition:     'src\audio_processing.doj'
        Attempted redefinition: 'src\reverb.doj']]></TEXT>
</MSG>
<MSG id='03377738' mid='li1050' type='Error' >
<TEXT><![CDATA['_apbuf0' ('apbuf0'): Multiply defined symbol in processor 'p0'.
        Initial definition:     'src\audio_processing.doj'
        Attempted redefinition: 'src\reverb.doj']]></TEXT>
</MSG>
<MSG id='033778F8' mid='li1050' type='Error' >
<TEXT><![CDATA['_apbuf1' ('apbuf1'): Multiply defined symbol in processor 'p0'.
        Initial definition:     'src\audio_processing.doj'
        Attempted redefinition: 'src\reverb.doj']]></TEXT>
</MSG>
<MSG id='03377AB8' mid='li1050' type='Error' >
<TEXT><![CDATA['_apbuf2' ('apbuf2'): Multiply defined symbol in processor 'p0'.
        Initial definition:     'src\audio_processing.doj'
        Attempted redefinition: 'src\reverb.doj']]></TEXT>
</MSG>
</DOCUMENT>
